linkedin_mcp_server/__init__.py
linkedin_mcp_server/__main__.py
linkedin_mcp_server/authentication.py
linkedin_mcp_server/cli.py
linkedin_mcp_server/cli_main.py
linkedin_mcp_server/error_handler.py
linkedin_mcp_server/exceptions.py
linkedin_mcp_server/logging_config.py
linkedin_mcp_server/server.py
linkedin_mcp_server/setup.py
linkedin_mcp_server/config/__init__.py
linkedin_mcp_server/config/loaders.py
linkedin_mcp_server/config/messages.py
linkedin_mcp_server/config/providers.py
linkedin_mcp_server/config/schema.py
linkedin_mcp_server/config/secrets.py
linkedin_mcp_server/drivers/__init__.py
linkedin_mcp_server/drivers/chrome.py
linkedin_mcp_server/tools/__init__.py
linkedin_mcp_server/tools/company.py
linkedin_mcp_server/tools/job.py
linkedin_mcp_server/tools/person.py
mseep_linkedin_mcp_server-1.4.1.dist-info/licenses/LICENSE
mseep_linkedin_mcp_server-1.4.1.dist-info/METADATA
mseep_linkedin_mcp_server-1.4.1.dist-info/WHEEL
mseep_linkedin_mcp_server-1.4.1.dist-info/entry_points.txt
mseep_linkedin_mcp_server-1.4.1.dist-info/top_level.txt
mseep_linkedin_mcp_server-1.4.1.dist-info/RECORD
