Metadata-Version: 2.4
Name: mseep-linkedin-mcp-server
Version: 1.4.1
Summary: MCP server for LinkedIn profile, company, and job scraping with Claude AI integration. Supports direct profile/company/job URL scraping with secure credential storage.
Author-email: mseep <support@skydeck.ai>
Requires-Python: >=3.12
License-File: LICENSE
Requires-Dist: fastmcp>=2.10.1
Requires-Dist: inquirer>=3.4.0
Requires-Dist: keyring>=25.6.0
Requires-Dist: linkedin-scraper
Requires-Dist: pyperclip>=1.9.0
Dynamic: license-file
